README.rst
setup.py
undoable.py
undoable.egg-info/PKG-INFO
undoable.egg-info/SOURCES.txt
undoable.egg-info/dependency_links.txt
undoable.egg-info/top_level.txt