Metadata-Version: 1.0
Name: undoable
Version: 0.3
Summary: Simple Python list and dict with undo/redo
Home-page: https://github.com/asrp/undoable
Author: asrp
Author-email: asrp@email.com
License: UNKNOWN
Keywords: callbacks undo observer
Platform: UNKNOWN
